vlbisim/__init__.py
vlbisim/vlbisim.py
vlbisim-0.1.1.dist-info/licenses/LICENSE
vlbisim-0.1.1.dist-info/METADATA
vlbisim-0.1.1.dist-info/WHEEL
vlbisim-0.1.1.dist-info/entry_points.txt
vlbisim-0.1.1.dist-info/top_level.txt
vlbisim-0.1.1.dist-info/RECORD
